django_clerk_sdk/__init__.py
django_clerk_sdk/config.py
django_clerk_sdk/core/__init__.py
django_clerk_sdk/core/auth/__init__.py
django_clerk_sdk/core/auth/clerk/__init__.py
django_clerk_sdk/core/auth/clerk/authentication.py
django_clerk_sdk/core/auth/clerk/middleware.py
django_clerk_sdk/core/auth/clerk/sdk.py
django_clerk_sdk/core/compat.py
django_clerk_sdk/core/conf.py
django_clerk_sdk/core/loading.py
django_clerk_sdk/core/signals.py
django_clerk_sdk/core/utils/__init__.py
django_clerk_sdk/core/utils/cache.py
django_clerk_sdk/core/utils/descriptors.py
django_clerk_sdk/defaults.py
django_clerk_sdk/users/__init__.py
django_clerk_sdk/users/admin.py
django_clerk_sdk/users/apps.py
django_clerk_sdk/users/migrations/0001_initial.py
django_clerk_sdk/users/migrations/__init__.py
django_clerk_sdk/users/models.py
django_clerk_sdk/utils/deprecation.py
django_clerk_sdk-0.2.0.dist-info/WHEEL
django_clerk_sdk-0.2.0.dist-info/entry_points.txt
django_clerk_sdk-0.2.0.dist-info/METADATA
django_clerk_sdk-0.2.0.dist-info/RECORD
