Metadata-Version: 2.3
Name: django-clerk-sdk
Version: 0.2.0
Summary: Lightweight Django integration for Clerk authentication and user syncing. 
Requires-Dist: clerk-backend-api>=3.3.1
Requires-Dist: django>=5.2.7
Requires-Dist: django-guardian>=3.2.0
Requires-Dist: django-rest-framework>=0.1.0
Requires-Dist: djangorestframework-stubs>=3.16.6
Requires-Dist: python-decouple
Requires-Python: >=3.14
